wordninja_enhanced/__init__.py
wordninja_enhanced/wordninja.py
wordninja_enhanced/resources/de_dict.txt.gz
wordninja_enhanced/resources/en_dict.txt.gz
wordninja_enhanced/resources/es_dict.txt.gz
wordninja_enhanced/resources/fr_dict.txt.gz
wordninja_enhanced/resources/it_dict.txt.gz
wordninja_enhanced/resources/pt_dict.txt.gz
wordninja_enhanced-3.1.0.dist-info/licenses/LICENSE
wordninja_enhanced-3.1.0.dist-info/METADATA
wordninja_enhanced-3.1.0.dist-info/WHEEL
wordninja_enhanced-3.1.0.dist-info/top_level.txt
wordninja_enhanced-3.1.0.dist-info/RECORD
