Metadata-Version: 2.4
Name: wordninja-enhanced
Version: 3.1.0
Summary: Probabilistically split concatenated words. Now with more functionality and languages!
Author: Tim Lodemann
License-Expression: MIT
Project-URL: Homepage, https://github.com/timminator/wordninja-enhanced
Project-URL: documentation, https://github.com/timminator/wordninja-enhanced/blob/master/README.md
Project-URL: Repository, https://github.com/timminator/wordninja-enhanced.git
Project-URL: Issues, https://github.com/timminator/wordninja-enhanced/issues
Keywords: text-processing,nlp,language,segmentation
Classifier: Intended Audience :: Developers
Classifier: Operating System :: OS Independent
Classifier: Programming Language :: Python :: 3
Classifier: Topic :: Text Processing :: Linguistic
Requires-Python: >=3.9
License-File: LICENSE
Dynamic: license-file
